{
	"$schema": "https://gobl.org/draft-0/envelope",
	"head": {
		"uuid": "8a51fd30-2a27-11ee-be56-0242ac120002",
		"dig": {
			"alg": "sha256",
			"val": "be4ee6903e80675fb357a3855c6e029fa308bd1d9f68e476f6f6c1d6e61ad9bb"
		}
	},
	"doc": {
		"$schema": "https://gobl.org/draft-0/bill/status",
		"$regime": "ES",
		"uuid": "0194c26e-e6c3-7b44-ad20-a2b3c4d5e6f7",
		"type": "system",
		"issue_date": "2025-04-15",
		"issue_time": "21:05:00",
		"series": "SS",
		"code": "00101",
		"supplier": {
			"name": "Provide One S.L.",
			"tax_id": {
				"country": "ES",
				"code": "B98602642"
			}
		},
		"lines": [
			{
				"index": 1,
				"key": "other",
				"description": "System was shutdown"
			}
		]
	}
}