{
  "$schema": "https://gobl.org/draft-0/tax/catalogue-def",
  "key": "untdid",
  "name": {
    "en": "UN/EDIFACT Data Elements"
  },
  "description": null,
  "extensions": [
    {
      "key": "untdid-document-type",
      "name": {
        "en": "UNTDID 1001 Document Type"
      },
      "desc": {
        "en": "UNTDID 1001 code used to describe the type of document. Ths list is based\non the [EN16931 code list](https://ec.europa.eu/digital-building-blocks/sites/display/DIGITAL/Registry+of+supporting+artefacts+to+implement+EN16931#RegistryofsupportingartefactstoimplementEN16931-Codelists)\nvalues table which focusses on invoices and payments.\n\nOther tax regimes and addons may use their own subset of codes."
      },
      "values": [
        {
          "value": "71",
          "name": {
            "en": "Request for payment"
          }
        },
        {
          "value": "80",
          "name": {
            "en": "Debit note related to goods or services"
          }
        },
        {
          "value": "81",
          "name": {
            "en": "Credit note related to goods or services"
          }
        },
        {
          "value": "82",
          "name": {
            "en": "Metered services invoice"
          }
        },
        {
          "value": "83",
          "name": {
            "en": "Credit note related to financial adjustments"
          }
        },
        {
          "value": "84",
          "name": {
            "en": "Debit note related to financial adjustments"
          }
        },
        {
          "value": "102",
          "name": {
            "en": "Tax notification"
          }
        },
        {
          "value": "130",
          "name": {
            "en": "Invoicing data sheet"
          }
        },
        {
          "value": "202",
          "name": {
            "en": "Direct payment valuation"
          }
        },
        {
          "value": "203",
          "name": {
            "en": "Provisional payment valuation"
          }
        },
        {
          "value": "204",
          "name": {
            "en": "Payment valuation"
          }
        },
        {
          "value": "211",
          "name": {
            "en": "Interim application for payment"
          }
        },
        {
          "value": "218",
          "name": {
            "en": "Final payment request based on completion of work"
          }
        },
        {
          "value": "219",
          "name": {
            "en": "Payment request for completed units"
          }
        },
        {
          "value": "261",
          "name": {
            "en": "Self billed credit note"
          }
        },
        {
          "value": "262",
          "name": {
            "en": "Consolidated credit note - goods and services"
          }
        },
        {
          "value": "295",
          "name": {
            "en": "Price variation invoice"
          }
        },
        {
          "value": "296",
          "name": {
            "en": "Credit note for price variation"
          }
        },
        {
          "value": "308",
          "name": {
            "en": "Delcredere credit note"
          }
        },
        {
          "value": "325",
          "name": {
            "en": "Proforma invoice"
          }
        },
        {
          "value": "326",
          "name": {
            "en": "Partial invoice"
          }
        },
        {
          "value": "380",
          "name": {
            "en": "Standard Invoice"
          }
        },
        {
          "value": "381",
          "name": {
            "en": "Credit note"
          }
        },
        {
          "value": "382",
          "name": {
            "en": "Commission note"
          }
        },
        {
          "value": "383",
          "name": {
            "en": "Debit note"
          }
        },
        {
          "value": "384",
          "name": {
            "en": "Corrected invoice"
          }
        },
        {
          "value": "385",
          "name": {
            "en": "Consolidated invoice"
          }
        },
        {
          "value": "386",
          "name": {
            "en": "Prepayment invoice"
          }
        },
        {
          "value": "387",
          "name": {
            "en": "Hire invoice"
          }
        },
        {
          "value": "388",
          "name": {
            "en": "Tax invoice"
          }
        },
        {
          "value": "389",
          "name": {
            "en": "Self-billed invoice"
          }
        },
        {
          "value": "390",
          "name": {
            "en": "Delcredere invoice"
          }
        },
        {
          "value": "393",
          "name": {
            "en": "Factored invoice"
          }
        },
        {
          "value": "394",
          "name": {
            "en": "Lease invoice"
          }
        },
        {
          "value": "395",
          "name": {
            "en": "Consignment invoice"
          }
        },
        {
          "value": "396",
          "name": {
            "en": "Factored credit note"
          }
        },
        {
          "value": "420",
          "name": {
            "en": "Optical Character Reading (OCR) payment credit note"
          }
        },
        {
          "value": "456",
          "name": {
            "en": "Debit advice"
          }
        },
        {
          "value": "457",
          "name": {
            "en": "Reversal of debit"
          }
        },
        {
          "value": "458",
          "name": {
            "en": "Reversal of credit"
          }
        },
        {
          "value": "527",
          "name": {
            "en": "Self billed debit note"
          }
        },
        {
          "value": "532",
          "name": {
            "en": "Forwarder's credit note"
          }
        },
        {
          "value": "553",
          "name": {
            "en": "Forwarder's invoice discrepancy report"
          }
        },
        {
          "value": "575",
          "name": {
            "en": "Insurer's invoice"
          }
        },
        {
          "value": "623",
          "name": {
            "en": "Forwarder's invoice"
          }
        },
        {
          "value": "633",
          "name": {
            "en": "Port charges documents"
          }
        },
        {
          "value": "751",
          "name": {
            "en": "Invoice information for accounting purposes"
          }
        },
        {
          "value": "780",
          "name": {
            "en": "Freight invoice"
          }
        },
        {
          "value": "817",
          "name": {
            "en": "Claim notification"
          }
        },
        {
          "value": "870",
          "name": {
            "en": "Consular invoice"
          }
        },
        {
          "value": "875",
          "name": {
            "en": "Partial construction invoice"
          }
        },
        {
          "value": "876",
          "name": {
            "en": "Partial final construction invoice"
          }
        },
        {
          "value": "877",
          "name": {
            "en": "Final construction invoice"
          }
        },
        {
          "value": "935",
          "name": {
            "en": "Customs invoice"
          }
        }
      ]
    },
    {
      "key": "untdid-payment-means",
      "name": {
        "en": "UNTDID 4461 Payment Means"
      },
      "desc": {
        "en": "UNTDID 4461 code used to describe the means of payment. This list is based on the\n[EN16931 code list](https://ec.europa.eu/digital-building-blocks/sites/display/DIGITAL/Registry+of+supporting+artefacts+to+implement+EN16931#RegistryofsupportingartefactstoimplementEN16931-Codelists)\nvalues table which focusses on invoices and payments."
      },
      "values": [
        {
          "value": "1",
          "name": {
            "en": "Instrument not defined"
          }
        },
        {
          "value": "2",
          "name": {
            "en": "Automated clearing house credit"
          }
        },
        {
          "value": "3",
          "name": {
            "en": "Automated clearing house debit"
          }
        },
        {
          "value": "4",
          "name": {
            "en": "ACH demand debit reversal"
          }
        },
        {
          "value": "5",
          "name": {
            "en": "ACH demand credit reversal"
          }
        },
        {
          "value": "6",
          "name": {
            "en": "ACH demand credit"
          }
        },
        {
          "value": "7",
          "name": {
            "en": "ACH demand debit"
          }
        },
        {
          "value": "8",
          "name": {
            "en": "Hold"
          }
        },
        {
          "value": "9",
          "name": {
            "en": "National or regional clearing"
          }
        },
        {
          "value": "10",
          "name": {
            "en": "In cash"
          }
        },
        {
          "value": "11",
          "name": {
            "en": "ACH savings credit reversal"
          }
        },
        {
          "value": "12",
          "name": {
            "en": "ACH savings debit reversal"
          }
        },
        {
          "value": "13",
          "name": {
            "en": "ACH savings credit"
          }
        },
        {
          "value": "14",
          "name": {
            "en": "ACH savings debit"
          }
        },
        {
          "value": "15",
          "name": {
            "en": "Bookentry credit"
          }
        },
        {
          "value": "16",
          "name": {
            "en": "Bookentry debit"
          }
        },
        {
          "value": "17",
          "name": {
            "en": "ACH demand cash concentration/disbursement (CCD) credit"
          }
        },
        {
          "value": "18",
          "name": {
            "en": "ACH demand cash concentration/disbursement (CCD) debit"
          }
        },
        {
          "value": "19",
          "name": {
            "en": "ACH demand corporate trade payment (CTP) credit"
          }
        },
        {
          "value": "20",
          "name": {
            "en": "Cheque"
          }
        },
        {
          "value": "21",
          "name": {
            "en": "Banker's draft"
          }
        },
        {
          "value": "22",
          "name": {
            "en": "Certified banker's draft"
          }
        },
        {
          "value": "23",
          "name": {
            "en": "Bank cheque (issued by a banking or similar establishment)"
          }
        },
        {
          "value": "24",
          "name": {
            "en": "Bill of exchange awaiting acceptance"
          }
        },
        {
          "value": "25",
          "name": {
            "en": "Certified cheque"
          }
        },
        {
          "value": "26",
          "name": {
            "en": "Local cheque"
          }
        },
        {
          "value": "27",
          "name": {
            "en": "ACH demand corporate trade payment (CTP) debit"
          }
        },
        {
          "value": "28",
          "name": {
            "en": "ACH demand corporate trade exchange (CTX) credit"
          }
        },
        {
          "value": "29",
          "name": {
            "en": "ACH demand corporate trade exchange (CTX) debit"
          }
        },
        {
          "value": "30",
          "name": {
            "en": "Credit transfer"
          }
        },
        {
          "value": "31",
          "name": {
            "en": "Debit transfer"
          }
        },
        {
          "value": "32",
          "name": {
            "en": "ACH demand cash concentration/disbursement plus (CCD+)"
          }
        },
        {
          "value": "33",
          "name": {
            "en": "ACH demand cash concentration/disbursement plus (CCD+)"
          }
        },
        {
          "value": "34",
          "name": {
            "en": "ACH prearranged payment and deposit (PPD)"
          }
        },
        {
          "value": "35",
          "name": {
            "en": "ACH savings cash concentration/disbursement (CCD) credit"
          }
        },
        {
          "value": "36",
          "name": {
            "en": "ACH savings cash concentration/disbursement (CCD) debit"
          }
        },
        {
          "value": "37",
          "name": {
            "en": "ACH savings corporate trade payment (CTP) credit"
          }
        },
        {
          "value": "38",
          "name": {
            "en": "ACH savings corporate trade payment (CTP) debit"
          }
        },
        {
          "value": "39",
          "name": {
            "en": "ACH savings corporate trade exchange (CTX) credit"
          }
        },
        {
          "value": "40",
          "name": {
            "en": "ACH savings corporate trade exchange (CTX) debit"
          }
        },
        {
          "value": "41",
          "name": {
            "en": "ACH savings cash concentration/disbursement plus (CCD+)"
          }
        },
        {
          "value": "42",
          "name": {
            "en": "Payment to bank account"
          }
        },
        {
          "value": "43",
          "name": {
            "en": "ACH savings cash concentration/disbursement plus (CCD+)"
          }
        },
        {
          "value": "44",
          "name": {
            "en": "Accepted bill of exchange"
          }
        },
        {
          "value": "45",
          "name": {
            "en": "Referenced home-banking credit transfer"
          }
        },
        {
          "value": "46",
          "name": {
            "en": "Interbank debit transfer"
          }
        },
        {
          "value": "47",
          "name": {
            "en": "Home-banking debit transfer"
          }
        },
        {
          "value": "48",
          "name": {
            "en": "Bank card"
          }
        },
        {
          "value": "49",
          "name": {
            "en": "Direct debit"
          }
        },
        {
          "value": "50",
          "name": {
            "en": "Payment by postgiro"
          }
        },
        {
          "value": "51",
          "name": {
            "en": "FR, norme 6 97-Telereglement CFONB (French Organisation for"
          }
        },
        {
          "value": "52",
          "name": {
            "en": "Urgent commercial payment"
          }
        },
        {
          "value": "53",
          "name": {
            "en": "Urgent Treasury Payment"
          }
        },
        {
          "value": "54",
          "name": {
            "en": "Credit card"
          }
        },
        {
          "value": "55",
          "name": {
            "en": "Debit card"
          }
        },
        {
          "value": "56",
          "name": {
            "en": "Bankgiro"
          }
        },
        {
          "value": "57",
          "name": {
            "en": "Standing agreement"
          }
        },
        {
          "value": "58",
          "name": {
            "en": "SEPA credit transfer"
          }
        },
        {
          "value": "59",
          "name": {
            "en": "SEPA direct debit"
          }
        },
        {
          "value": "60",
          "name": {
            "en": "Promissory note"
          }
        },
        {
          "value": "61",
          "name": {
            "en": "Promissory note signed by the debtor"
          }
        },
        {
          "value": "62",
          "name": {
            "en": "Promissory note signed by the debtor and endorsed by a bank"
          }
        },
        {
          "value": "63",
          "name": {
            "en": "Promissory note signed by the debtor and endorsed by a"
          }
        },
        {
          "value": "64",
          "name": {
            "en": "Promissory note signed by a bank"
          }
        },
        {
          "value": "65",
          "name": {
            "en": "Promissory note signed by a bank and endorsed by another"
          }
        },
        {
          "value": "66",
          "name": {
            "en": "Promissory note signed by a third party"
          }
        },
        {
          "value": "67",
          "name": {
            "en": "Promissory note signed by a third party and endorsed by a"
          }
        },
        {
          "value": "68",
          "name": {
            "en": "Online payment service"
          }
        },
        {
          "value": "69",
          "name": {
            "en": "Transfer Advice"
          }
        },
        {
          "value": "70",
          "name": {
            "en": "Bill drawn by the creditor on the debtor"
          }
        },
        {
          "value": "74",
          "name": {
            "en": "Bill drawn by the creditor on a bank"
          }
        },
        {
          "value": "75",
          "name": {
            "en": "Bill drawn by the creditor, endorsed by another bank"
          }
        },
        {
          "value": "76",
          "name": {
            "en": "Bill drawn by the creditor on a bank and endorsed by a"
          }
        },
        {
          "value": "77",
          "name": {
            "en": "Bill drawn by the creditor on a third party"
          }
        },
        {
          "value": "78",
          "name": {
            "en": "Bill drawn by creditor on third party, accepted and"
          }
        },
        {
          "value": "91",
          "name": {
            "en": "Not transferable banker's draft"
          }
        },
        {
          "value": "92",
          "name": {
            "en": "Not transferable local cheque"
          }
        },
        {
          "value": "93",
          "name": {
            "en": "Reference giro"
          }
        },
        {
          "value": "94",
          "name": {
            "en": "Urgent giro"
          }
        },
        {
          "value": "95",
          "name": {
            "en": "Free format giro"
          }
        },
        {
          "value": "96",
          "name": {
            "en": "Requested method for payment was not used"
          }
        },
        {
          "value": "97",
          "name": {
            "en": "Clearing between partners"
          }
        },
        {
          "value": "98",
          "name": {
            "en": "JP, Electronically Recorded Monetary Claims"
          }
        },
        {
          "value": "ZZZ",
          "name": {
            "en": "Mutually defined"
          }
        }
      ]
    },
    {
      "key": "untdid-tax-category",
      "name": {
        "en": "UNTDID 3505 Tax Category"
      },
      "desc": {
        "en": "UNTDID 5305 code used to describe the applicable duty/tax/fee category. There are\nmultiple versions and subsets of this table so regimes and addons may need to filter\noptions for a specific subset of values.\n\nData from https://unece.org/fileadmin/DAM/trade/untdid/d16b/tred/tred5305.htm."
      },
      "values": [
        {
          "value": "A",
          "name": {
            "en": "Mixed tax rate"
          }
        },
        {
          "value": "AA",
          "name": {
            "en": "Lower rate"
          }
        },
        {
          "value": "AB",
          "name": {
            "en": "Exempt for resale"
          }
        },
        {
          "value": "AC",
          "name": {
            "en": "Exempt for resale"
          }
        },
        {
          "value": "AD",
          "name": {
            "en": "Value Added Tax (VAT) due from a previous invoice"
          }
        },
        {
          "value": "AE",
          "name": {
            "en": "VAT Reverse Charge"
          }
        },
        {
          "value": "B",
          "name": {
            "en": "Transferred (VAT)"
          }
        },
        {
          "value": "C",
          "name": {
            "en": "Duty paid by supplier"
          }
        },
        {
          "value": "D",
          "name": {
            "en": "Value Added Tax (VAT) margin scheme - travel agents"
          }
        },
        {
          "value": "E",
          "name": {
            "en": "Exempt from tax"
          }
        },
        {
          "value": "F",
          "name": {
            "en": "Value Added Tax (VAT) margin scheme - second-hand goods"
          }
        },
        {
          "value": "G",
          "name": {
            "en": "Free export item, tax not charged"
          }
        },
        {
          "value": "H",
          "name": {
            "en": "Higher rate"
          }
        },
        {
          "value": "I",
          "name": {
            "en": "Value Added Tax (VAT) margin scheme - works of art"
          }
        },
        {
          "value": "J",
          "name": {
            "en": "Value Added Tax (VAT) margin scheme - collector's items and antiques"
          }
        },
        {
          "value": "K",
          "name": {
            "en": "VAT exempt for EEA intra-community supply of goods and services"
          }
        },
        {
          "value": "L",
          "name": {
            "en": "Canary Islands general indirect tax"
          }
        },
        {
          "value": "M",
          "name": {
            "en": "Tax for production, services and importation in Ceuta and Melilla"
          }
        },
        {
          "value": "O",
          "name": {
            "en": "Services outside scope of tax"
          }
        },
        {
          "value": "S",
          "name": {
            "en": "Standard Rate"
          }
        },
        {
          "value": "Z",
          "name": {
            "en": "Zero rated goods"
          }
        }
      ]
    }
  ]
}